{
  "id": "MEL-LPP-008",
  "title": "Crime Prevention Through Environmental Design of",
  "instrument_type": "LPP",
  "issuing_authority": "City of Melville",
  "version_date": "August 2019",
  "pages": 3,
  "key_provisions": [
    {
      "heading": "1 Design Elements",
      "summary": "(a) The development is to have a view of the adjacent footpath or road reserve of the"
    },
    {
      "heading": "1.1 Passive Surveillance",
      "summary": "(a) The development is to have a view of the adjacent footpath or road reserve of the"
    },
    {
      "heading": "1.2 Graffiti",
      "summary": "(a) Building designs are to avoid blank walls or fences which will be accessible from the"
    },
    {
      "heading": "1.3 Fencing",
      "summary": "(a) Fencing within the front setback of properties is to be visually permeable above 1.2m"
    },
    {
      "heading": "1.4 Design Elements for Non-Residential and Multiple Dwelling Developments",
      "summary": "(a) Developments are not to incorporate blind corners adjacent to pedestrian paths."
    },
    {
      "heading": "2 Variations to Design Elements",
      "summary": "Where variations or alternative measures are proposed to the Design Elements in Part 1"
    },
    {
      "heading": "3 Advertising",
      "summary": "Variations to the above design elements need not be advertised to adjoining property"
    },
    {
      "heading": "4 Notes",
      "summary": "Where any of the above provisions result in developments which are inconsistent with the"
    }
  ],
  "cross_references": [
    "LPP1.8",
    "Local Planning Scheme No. 6",
    "Planning and Development Act 2005",
    "R-Codes",
    "Residential Design Codes",
    "Residential Design Codes Volume 1",
    "Residential Design Codes Volume 2",
    "State Planning Policy 7.3"
  ],
  "tables_skipped": false,
  "extracted_at": "2026-06-09T22:38:13Z"
}