{
  "id": "PB-007",
  "title": "Planning Bulletin 107/2012",
  "instrument_type": "planning_bulletin",
  "issuing_authority": "Western Australian Planning Commission",
  "version_date": "August 2012",
  "pages": 2,
  "key_provisions": [
    {
      "heading": "140 William Street",
      "summary": "The State Administrative Tribunal (SAT) The Model Subdivision Conditions PERTH WA 6000"
    }
  ],
  "cross_references": [
    "Planning Bulletin 107/2012"
  ],
  "tables_skipped": false,
  "extracted_at": "2026-06-09T22:36:10Z"
}